MANIFEST.in
README.rst
setup.py
datasquirrel/__init__.py
datasquirrel/_version.py
datasquirrel/btcc.py
datasquirrel/luno.py
datasquirrel/utils.py
datasquirrel.egg-info/PKG-INFO
datasquirrel.egg-info/SOURCES.txt
datasquirrel.egg-info/dependency_links.txt
datasquirrel.egg-info/requires.txt
datasquirrel.egg-info/top_level.txt