Metadata-Version: 1.1
Name: datasquirrel
Version: 0.0.1a1
Summary: Crypto and standar currency API data getter and saver
Home-page: https://github.com/grantstephens/data-squirrel
Author: Grant Stephens
Author-email: grant@stephens.co.za
License: MIT
Download-URL: https://github.com/grantstephens/data-squirrel/tarball/0.0.1a1
Keywords: cryptocurrency api data hdf5
Platform: UNKNOWN
Classifier: Development Status :: 3 - Alpha
Classifier: Intended Audience :: Developers
Classifier: License :: OSI Approved :: MIT License
Classifier: Topic :: Office/Business :: Financial
Classifier: Topic :: Utilities
Classifier: Programming Language :: Python :: 3
Classifier: Programming Language :: Python :: 3.2
Classifier: Programming Language :: Python :: 3.3
Classifier: Programming Language :: Python :: 3.4
Classifier: Programming Language :: Python :: 3.5
Classifier: Programming Language :: Python :: 3.6
Classifier: Programming Language :: Python :: 3 :: Only
